{
    "header": {
        "header-1": [
            "header/h-1",
            "header",
            "header-1.png",
            "Header 1",
            "51px"
        ],
        "header-2": [
            "header/h-2",
            "header",
            "header-2.png",
            "Header 2",
            "51px"
        ],
        "header-3": [
            "header/h-3",
            "header",
            "header-3.png",
            "Header 3",
            "51px"
        ],
        "header-4": [
            "header/h-4",
            "header",
            "header-4.png",
            "Header 4",
            "51px"
        ],
        "header-5": [
            "header/h-5",
            "header",
            "header-5.png",
            "Header 5",
            "51px"
        ],
        "header-6": [
            "header/h-6",
            "header",
            "header-6.png",
            "Header 6",
            "51px"
        ],
        "header-7": [
            "header/h-7",
            "header",
            "4bce78ba6e87a21236f52f144f940c85.png",
            "Header big logo"
        ],
        "header-8": [
            "header/h-8",
            "header",
            "14ed823d93896fefe52afb5bf1c49e7c.png",
            "Header 8"
        ],
        "header-9": [
            "header/h-9",
            "header",
            "92c9a0f2d572a5687a9c7fa981b755a9.png",
            "Header 9"
        ]
    },
    "boxes": {
        "boxes-1": [
            "boxes/b-1",
            "body",
            "boxes-1.png",
            "boxes 1"
        ],
        "boxes-2": [
            "boxes/b-2",
            "body",
            "boxes-2.png",
            "boxes 2"
        ],
        "boxes-3": [
            "boxes/b-3",
            "body",
            "7e07c3213f76f5d7696ff597e20ffaec.png",
            "dfg"
        ],
        "boxes-4": [
            "boxes/b-4",
            "body",
            "f6e92256e2a7d837302b5a870409735a.png",
            "Boxes 4"
        ],
        "boxes-5": [
            "boxes/b-5",
            "body",
            "012d813c37a4d74ba3672030950a0df6.png",
            "Boxes 5"
        ],
        "boxes-6": [
            "boxes/b-6",
            "body",
            "ebee8771e948779386090f03c6c90967.png",
            "Box 6"
        ],
        "boxes-7": [
            "boxes/b-7",
            "body",
            "caeccd0e19fd8dc006e8c1067ce841a3.png",
            "Box 7"
        ],
        "boxes-8": [
            "boxes/b-8",
            "body",
            "922a03d8dd20e732ac2fe2afca8a368d.png",
            "Box 8"
        ],
        "boxes-9": [
            "boxes/b-9",
            "body",
            "7fddc880f37b1a485026fcb2e23f4500.png",
            "Box 9"
        ],
        "boxes-10": [
            "boxes/b-10",
            "body",
            "188f313149b0867b2fce149b24caa2af.png",
            "Box 10"
        ],
        "boxes-11": [
            "boxes/b-11",
            "body",
            "cd82c9042e10749f5d73e06a56f1c123.png",
            "Box 11"
        ],
        "boxes-12": [
            "boxes/b-12",
            "body",
            "a2030ddf1f54c3028f0f56d9ecc2e7de.png",
            "Box 12"
        ],
        "boxes-13": [
            "boxes/b-13",
            "body",
            "6877ce036fd0106384d814741ac8d220.png",
            "Boxes 13"
        ]
    },
    "slider": {
        "slider-1": [
            "slider/s-1",
            "body",
            "slider-1.png",
            "slider 1"
        ],
        "slider-2": [
            "slider/s-2",
            "body",
            "slider-2.png",
            "slider 2"
        ],
        "slider-3": [
            "slider/s-3",
            "body",
            "5ffa74078ea5078338b0566f1abbdc6c.png",
            "Slider 3"
        ],
        "slider-4": [
            "slider/s-4",
            "body",
            "28c6e7a585711fdaf6723d6668dd9dd1.png",
            "Slider 4"
        ],
        "slider-5": [
            "slider/s-5",
            "body",
            "220d3912497f2ce4217ca71314f1dfd6.png",
            "Slider 5"
        ]
    },
    "banner": {},
    "carousel": {
        "carousel-1": [
            "carousel/c-1",
            "body",
            "carousel-1.png",
            "carousel 1"
        ],
        "carousel-2": [
            "carousel/c-2",
            "body",
            "carousel-2.png",
            "carousel 2"
        ],
        "carousel-3": [
            "carousel/c-3",
            "body",
            "carousel-3.png",
            "carousel 3"
        ],
        "carousel-4": [
            "carousel/c-4",
            "body",
            "carousel-4.png",
            "carousel 4"
        ],
        "carousel-5": [
            "carousel/c-5",
            "body",
            "dff90ca9664bfb263b1e433e991421dc.png",
            "Carousel 5"
        ],
        "carousel-6": [
            "carousel/c-6",
            "body",
            "80aba5b538642b90e6ebc231c9b68ef0.png",
            "Carousel 6"
        ],
        "carousel-7": [
            "carousel/c-7",
            "body",
            "0748873f3617c58a2f9e5d7e93dd34ae.png",
            "Carousel 7"
        ]
    },
    "news": {
        "news-1": [
            "news/n-1",
            "body",
            "news-1.png",
            "news 1"
        ],
        "news-2": [
            "news/n-2",
            "body",
            "news-2.png",
            "news 2"
        ],
        "news-3": [
            "news/n-3",
            "body",
            "news-3.png",
            "news 3"
        ],
        "news-4": [
            "news/n-4",
            "body",
            "64ce8b7f56c7d77db45e14cdc4a08f02.png",
            "News 4"
        ]
    },
    "news-details": {
        "news-details-1": [
            "news-details/n-1",
            "body",
            "d692c21877284337d23b07caaa0d40f5.png",
            "News Details 1 with stycky"
        ]
    },
    "shop": {
        "shop-1": [
            "shop/s-1",
            "body",
            "shop-1.png",
            "shop 1"
        ],
        "shop-2": [
            "shop/s-2",
            "body",
            "shop-2.png",
            "shop 2"
        ],
        "shop-3": [
            "shop/s-3",
            "body",
            "c041b486fa87ef9cca1f9beb51fc8f48.png",
            "Shop 3 - Quick view"
        ]
    },
    "shop-details": {
        "shop-details-1": [
            "shop-details/s-1",
            "body",
            "shop-details-1.png",
            "shop-details 1"
        ],
        "shop-details-2": [
            "shop-details/s-2",
            "body",
            "shop-details-2.png",
            "shop-details 2"
        ],
        "shop-details-3": [
            "shop-details/s-3",
            "body",
            "shop-details-3.png",
            "shop-details 3"
        ]
    },
    "gallery": {
        "gallery-1": [
            "gallery/g-1",
            "body",
            "gallery-1.png",
            "gallery 1"
        ],
        "gallery-2": [
            "gallery/g-2",
            "body",
            "711d2a1733005cd9ab00016753036e06.png",
            "Gallery Video"
        ],
        "gallery-3": [
            "gallery/g-3",
            "body",
            "0157ebd88a540ff4f65be0b6fe5424a0.png",
            "Gallery Video/Image/Hover"
        ],
        "gallery-4": [
            "gallery/g-4",
            "body",
            "7afbbb96fbb667c6c84ae157f84256d8.png",
            "Gallery 4"
        ]
    },
    "form": {
        "form-1": [
            "form/f-1",
            "body",
            "form-1.png",
            "form 1"
        ],
        "form-2": [
            "form/f-2",
            "body",
            "form-2.png",
            "form 2"
        ],
        "form-3": [
            "form/f-3",
            "body",
            "form-3.png",
            "form 3"
        ],
        "form-4": [
            "form/f-4",
            "body",
            "form-4.png",
            "form 4"
        ],
        "form-5": [
            "form/f-5",
            "body",
            "888e8edb4297291eef77a66acfe22cd0.png",
            "Form 5"
        ],
        "form-6": [
            "form/f-6",
            "body",
            "c486f373e434056da0d1fbe8484efec9.png",
            "Form 6"
        ],
        "form-7": [
            "form/f-7",
            "body",
            "dae021b08db57f4fb085402219b074d6.png",
            "Form 7"
        ]
    },
    "map": {
        "map-1": [
            "map/m-1",
            "body",
            "map-1.png",
            "map 1"
        ],
        "map-2": [
            "map/m-2",
            "body",
            "map-2.png",
            "map 2"
        ]
    },
    "tagline": {
        "tagline-1": [
            "tagline/t-1",
            "body",
            "tagline-1.png",
            "tagline 1"
        ],
        "tagline-2": [
            "tagline/t-2",
            "body",
            "tagline-2.png",
            "tagline 2"
        ],
        "tagline-3": [
            "tagline/t-3",
            "body",
            "tagline-3.png",
            "tagline 3"
        ],
        "tagline-4": [
            "tagline/t-4",
            "body",
            "tagline-4.png",
            "tagline 4"
        ],
        "tagline-5": [
            "tagline/t-5",
            "body",
            "tagline-5.png",
            "tagline 5"
        ],
        "tagline-6": [
            "tagline/t-6",
            "body",
            "tagline-6.png",
            "tagline 6"
        ],
        "tagline-7": [
            "tagline/t-7",
            "body",
            "tagline-7.png",
            "tagline 7"
        ],
        "tagline-8": [
            "tagline/t-8",
            "body",
            "tagline-8.png",
            "tagline 8"
        ]
    },
    "footer": {
        "footer-1": [
            "footer/f-1",
            "footer",
            "footer-1.png",
            "footer 1"
        ],
        "footer-2": [
            "footer/f-2",
            "footer",
            "footer-2.png",
            "footer 2"
        ],
        "footer-3": [
            "footer/f-3",
            "footer",
            "footer-3.png",
            "footer 3"
        ],
        "footer-4": [
            "footer/f-4",
            "footer",
            "footer-4.png",
            "footer 4"
        ],
        "footer-5": [
            "footer/f-5",
            "footer",
            "footer-5.png",
            "footer 5"
        ],
        "footer-6": [
            "footer/f-6",
            "footer",
            "4a39521b55cd4e039df619985f7ef78f.png",
            "Footer 6"
        ],
        "footer-7": [
            "footer/f-7",
            "footer",
            "004ffbce90efe6c8e778bbd77bcbf801.png",
            "Footer 7"
        ],
        "footer-8": [
            "footer/f-8",
            "footer",
            "acb1c94c08f2e71c0787442fdc2f630c.png",
            "Footer 8"
        ],
        "footer-9": [
            "footer/f-9",
            "footer",
            "efe7f75308d47e016379be988bf19c16.png",
            "Footer 9"
        ]
    }
}